rli/__init__.py
rli/cli.py
rli/commands/__init__.py
rli/commands/cmd_deploy.py
rli/commands/cmd_github.py
rli/commands/cmd_smoke.py
rli/config.py
rli/constants.py
rli/deploy.py
rli/docker.py
rli/exceptions.py
rli/git.py
rli/github.py
rli/utils/__init__.py
rli/utils/bash.py
rli-0.1.0.dist-info/entry_points.txt
rli-0.1.0.dist-info/WHEEL
rli-0.1.0.dist-info/METADATA
rli-0.1.0.dist-info/RECORD
