Metadata-Version: 2.1
Name: rli
Version: 0.1.0
Summary: My CLI tool to automate common tasks.
License: MIT
Author: luke.shay
Author-email: luke.shay@vertexvis.com
Requires-Python: >=3.7,<4.0
Classifier: License :: OSI Approved :: MIT License
Classifier: Programming Language :: Python :: 3
Classifier: Programming Language :: Python :: 3.7
Classifier: Programming Language :: Python :: 3.8
Requires-Dist: PyGithub (>=1.47,<2.0)
Requires-Dist: click (>=7.1.1,<8.0.0)
Requires-Dist: pynacl (>=1.3.0,<2.0.0)
